README.md
setup.py
src/concurrent_log/__init__.py
src/concurrent_log.egg-info/PKG-INFO
src/concurrent_log.egg-info/SOURCES.txt
src/concurrent_log.egg-info/dependency_links.txt
src/concurrent_log.egg-info/requires.txt
src/concurrent_log.egg-info/top_level.txt