Metadata-Version: 2.1
Name: concurrent_log
Version: 1.0.1
Summary: 多进程并发日志处理器
Home-page: https://github.com/huanghyw/concurrent_log
Author: HuangYiwei
Author-email: huanghyw@gmail.com
License: UNKNOWN
Platform: UNKNOWN
Classifier: Programming Language :: Python :: 3
Classifier: License :: OSI Approved :: MIT License
Classifier: Operating System :: OS Independent
Requires-Python: >=3.6
